{
    "struct":
    [
        {
            "unknown_0x00": ">float32",
            "unknown_0x04": ">float32",
            "unknown_0x08": ">float32",
            "unknown_0x0C": ">int32",
            "unknown_0x10": ">int32",
            "unknown_0x14": ">int32",
            "unknown_0x18": ">int32",
            "unknown_0x1C": ">int32",
            "unknown_0x20": ">int32",
            "unknown_0x24": ">int32",
            "unknown_0x28": ">int32",
            "unknown_0x2C": ">int32",
            "color_1"     : ">color128",
            "color_2"     : ">color128",
            "Light Type"  : ">sjis_string",
            "unknown_0x54": ">pad32",
            "unknown_0x58": ">pad32",
            "unknown_0x5C": ">pad32"
        }
    ]
}
